djadminshield/__init__.py
djadminshield/admin.py
djadminshield/asgi.py
djadminshield/models.py
djadminshield/settings.py
djadminshield/urls.py
djadminshield/views.py
djadminshield/wsgi.py
djadminshield/migrations/0001_initial.py
djadminshield/migrations/0002_unauthorizedaccessattempt_description.py
djadminshield/migrations/__init__.py
djadminshield/templates/djadminshield/admin/login.html
djadminshield-0.1.0.dist-info/LICENSE
djadminshield-0.1.0.dist-info/METADATA
djadminshield-0.1.0.dist-info/WHEEL
djadminshield-0.1.0.dist-info/top_level.txt
djadminshield-0.1.0.dist-info/RECORD
