Metadata-Version: 2.1
Name: djadminshield
Version: 0.1.0
Summary: A Django library to secure the admin panel by faking login pages and logging attempts.
Home-page: https://github.com/Rivindhu/djadminshield
Author: Kudamage Rivindhu Venuka Geeneth
Author-email: rivindhu98@gmail.com
License: MIT
Classifier: Framework :: Django
Classifier: Intended Audience :: Developers
Classifier: License :: OSI Approved :: MIT License
License-File: LICENSE
Requires-Dist: PyYAML==6.0.2
Requires-Dist: ua-parser==1.0.0
Requires-Dist: ua-parser-builtins==0.18.0.post1
Requires-Dist: user-agents==2.2.0
